proteinbert_pytorch/__init__.py
proteinbert_pytorch/proteinbert_pytorch.py
proteinbert_pytorch_reproduction-0.0.2.dist-info/METADATA
proteinbert_pytorch_reproduction-0.0.2.dist-info/WHEEL
proteinbert_pytorch_reproduction-0.0.2.dist-info/top_level.txt
proteinbert_pytorch_reproduction-0.0.2.dist-info/RECORD
